health_multimodal/__init__.py
health_multimodal/common/__init__.py
health_multimodal/common/device.py
health_multimodal/common/visualization.py
health_multimodal/image/__init__.py
health_multimodal/image/inference_engine.py
health_multimodal/image/utils.py
health_multimodal/image/data/__init__.py
health_multimodal/image/data/io.py
health_multimodal/image/data/transforms.py
health_multimodal/image/model/__init__.py
health_multimodal/image/model/encoder.py
health_multimodal/image/model/model.py
health_multimodal/image/model/modules.py
health_multimodal/image/model/pretrained.py
health_multimodal/image/model/resnet.py
health_multimodal/image/model/transformer.py
health_multimodal/image/model/types.py
health_multimodal/text/__init__.py
health_multimodal/text/inference_engine.py
health_multimodal/text/utils.py
health_multimodal/text/data/__init__.py
health_multimodal/text/data/io.py
health_multimodal/text/model/__init__.py
health_multimodal/text/model/configuration_cxrbert.py
health_multimodal/text/model/modelling_cxrbert.py
health_multimodal/vlp/__init__.py
health_multimodal/vlp/inference_engine.py
hi_ml_multimodal-0.2.2.dist-info/METADATA
hi_ml_multimodal-0.2.2.dist-info/WHEEL
hi_ml_multimodal-0.2.2.dist-info/top_level.txt
hi_ml_multimodal-0.2.2.dist-info/RECORD
