Metadata-Version: 2.1
Name: hi-ml-multimodal
Version: 0.2.2
Summary: Microsoft Health Futures package to work with multi-modal health data
Home-page: https://github.com/microsoft/hi-ml
Author: Biomedical Imaging Team @ Microsoft Health Futures
Author-email: innereyedev@microsoft.com
License: MIT License
Classifier: Development Status :: 3 - Alpha
Classifier: Intended Audience :: Science/Research
Classifier: Topic :: Scientific/Engineering :: Medical Science Apps.
Classifier: License :: OSI Approved :: MIT License
Classifier: Programming Language :: Python :: 3.9
Requires-Dist: huggingface-hub
Requires-Dist: matplotlib
Requires-Dist: Pillow
Requires-Dist: pydicom
Requires-Dist: scikit-image
Requires-Dist: SimpleITK
Requires-Dist: timm
Requires-Dist: torch
Requires-Dist: torchvision
Requires-Dist: transformers
